htmltext/__init__.py
htmltext/example.py
htmltext/htmltext.py
htmltext-0.0.7.dist-info/LICENSE
htmltext-0.0.7.dist-info/METADATA
htmltext-0.0.7.dist-info/WHEEL
htmltext-0.0.7.dist-info/top_level.txt
htmltext-0.0.7.dist-info/RECORD
