Metadata-Version: 2.1
Name: htmltext
Version: 0.0.7
Summary: Get title and main body text from an article in a web page